Morztypes_LolosharaGd/Morztypes.py
Morztypes_LolosharaGd/__init__.py
morztypes-0.0.2.dist-info/licenses/LICENSE
morztypes-0.0.2.dist-info/METADATA
morztypes-0.0.2.dist-info/WHEEL
morztypes-0.0.2.dist-info/top_level.txt
morztypes-0.0.2.dist-info/RECORD
