Metadata-Version: 2.4
Name: Morztypes
Version: 0.0.2
Summary: My small library for types like Vector2&3
Author-email: LolosharaGd <lolikbrawl5@gmail.com>
License-Expression: MIT
Project-URL: Homepage, https://github.com/LolosharaGd/Morztypes
Project-URL: Issues, https://github.com/LolosharaGd/Morztypes/issues
Classifier: Programming Language :: Python :: 3
Classifier: Operating System :: OS Independent
Requires-Python: >=3.9
License-File: LICENSE
Dynamic: license-file
